pagium/__init__.py
pagium/controls.py
pagium/hooks.py
pagium/matchers.py
pagium/page.py
pagium/utils.py
pagium/webdriver.py
pagium-0.0.18.dist-info/METADATA
pagium-0.0.18.dist-info/WHEEL
pagium-0.0.18.dist-info/top_level.txt
pagium-0.0.18.dist-info/RECORD
